Workbook

Sheet UAT Checklist
A1: Sr No | B1: Module | C1: Section | D1: Test Case ID | E1: Checkpoint | F1: Steps | G1: Expected Result | H1: Priority | I1: Rushikesh | J1: Aditi | K1: Siddhi | L1: Chinmay | M1: Tanishq | N1: Overall Status | O1: Remarks / Defect ID
A2: 1 | B2: Authentication & Session | C2: Login | D2: 1.1.1 | E2: Valid login with OTP | F2: Enter valid username + password + OTP → Submit | G2: Session created, redirect to dashboard, LoginLog recorded | H2: Critical | I2: ☑ | J2: ☐ | K2: ☑ | L2: ☐ | M2: ☐ | N2: =IF(COUNTIF(I2:L2,"☑")=4,"Complete",IF(COUNTIF(I2:L2,"☑")>0,"In Progress","Pending")) -> In Progress
A3: 2 | B3: Authentication & Session | C3: Login | D3: 1.1.2 | E3: Wrong password | F3: Enter valid username + wrong password → Submit | G3: "Invalid credentials" error, failedLoginAttempts incremented | H3: Critical | I3: ☑ | J3: ☐ | K3: ☑ | L3: ☐ | M3: ☐ | N3: =IF(COUNTIF(I3:L3,"☑")=4,"Complete",IF(COUNTIF(I3:L3,"☑")>0,"In Progress","Pending")) -> In Progress
A4: 3 | B4: Authentication & Session | C4: Login | D4: 1.1.3 | E4: Wrong OTP | F4: Enter valid creds + wrong OTP → Submit | G4: "Invalid OTP" error | H4: Critical | I4: ☑ | J4: ☐ | K4: ☑ | L4: ☐ | M4: ☐ | N4: =IF(COUNTIF(I4:L4,"☑")=4,"Complete",IF(COUNTIF(I4:L4,"☑")>0,"In Progress","Pending")) -> In Progress
A5: 4 | B5: Authentication & Session | C5: Login | D5: 1.1.4 | E5: Account lockout after 5 attempts | F5: Enter wrong password 5 times | G5: Account locked for 15 min, "Account locked" message | H5: Critical | I5: ☐ | J5: ☐ | K5: ☐ | L5: ☐ | M5: ☐ | N5: =IF(COUNTIF(I5:L5,"☑")=4,"Complete",IF(COUNTIF(I5:L5,"☑")>0,"In Progress","Pending")) -> Pending | O5: I entered 5 times wrong password but Accountant is not locked
A6: 5 | B6: Authentication & Session | C6: Login | D6: 1.1.5 | E6: Login while locked | F6: Wait < 15 min, enter correct creds | G6: "Account locked" even with correct creds | H6: High | I6: ☐ | J6: ☐ | K6: ☐ | L6: ☐ | M6: ☐ | N6: =IF(COUNTIF(I6:L6,"☑")=4,"Complete",IF(COUNTIF(I6:L6,"☑")>0,"In Progress","Pending")) -> Pending | O6: Account wasn’t locked, so I didn’t check
A7: 6 | B7: Authentication & Session | C7: Login | D7: 1.1.6 | E7: Login after lockout expires | F7: Wait > 15 min, enter correct creds | G7: Login succeeds, failedLoginAttempts reset | H7: High | I7: ☐ | J7: ☐ | K7: ☐ | L7: ☐ | M7: ☐ | N7: =IF(COUNTIF(I7:L7,"☑")=4,"Complete",IF(COUNTIF(I7:L7,"☑")>0,"In Progress","Pending")) -> Pending | O7: Account wasn’t locked, so I didn’t check
A8: 7 | B8: Authentication & Session | C8: Login | D8: 1.1.7 | E8: Expired password (90 days) | F8: Login with creds where passwordChangedAt > 90 days | G8: Login succeeds but mustChangePassword=true, redirect to /account/security | H8: High | I8: ☐ | J8: ☐ | K8: ☐ | L8: ☐ | M8: ☐ | N8: =IF(COUNTIF(I8:L8,"☑")=4,"Complete",IF(COUNTIF(I8:L8,"☑")>0,"In Progress","Pending")) -> Pending
A9: 8 | B9: Authentication & Session | C9: Login | D9: 1.1.8 | E9: Inactive user login | F9: Deactivate user, attempt login | G9: Login rejected | H9: Critical | I9: ☐ | J9: ☐ | K9: ☐ | L9: ☐ | M9: ☐ | N9: =IF(COUNTIF(I9:L9,"☑")=4,"Complete",IF(COUNTIF(I9:L9,"☑")>0,"In Progress","Pending")) -> Pending | O9: I didn’t check it because deactivation was not working
A10: 9 | B10: Authentication & Session | C10: Login | D10: 1.1.9 | E10: Empty username | F10: Submit with blank username | G10: Validation error | H10: Medium | I10: ☑ | J10: ☐ | K10: ☑ | L10: ☐ | M10: ☐ | N10: =IF(COUNTIF(I10:L10,"☑")=4,"Complete",IF(COUNTIF(I10:L10,"☑")>0,"In Progress","Pending")) -> In Progress
A11: 10 | B11: Authentication & Session | C11: Login | D11: 1.1.10 | E11: Empty password | F11: Submit with blank password | G11: Validation error | H11: Medium | I11: ☑ | J11: ☐ | K11: ☑ | L11: ☐ | M11: ☐ | N11: =IF(COUNTIF(I11:L11,"☑")=4,"Complete",IF(COUNTIF(I11:L11,"☑")>0,"In Progress","Pending")) -> In Progress
A12: 11 | B12: Authentication & Session | C12: Login | D12: 1.1.11 | E12: Late login detection | F12: Login after work start time + grace minutes (non-admin) | G12: LoginLog recorded with isLate=true | H12: High | I12: ☑ | J12: ☐ | K12: ☑ | L12: ☐ | M12: ☐ | N12: =IF(COUNTIF(I12:L12,"☑")=4,"Complete",IF(COUNTIF(I12:L12,"☑")>0,"In Progress","Pending")) -> In Progress
A13: 12 | B13: Authentication & Session | C13: Login | D13: 1.1.12 | E13: On-time login | F13: Login before work start time + grace (non-admin) | G13: LoginLog with isLate=false | H13: High | I13: ☐ | J13: ☐ | K13: ☐ | L13: ☐ | M13: ☐ | N13: =IF(COUNTIF(I13:L13,"☑")=4,"Complete",IF(COUNTIF(I13:L13,"☑")>0,"In Progress","Pending")) -> Pending
A14: 13 | B14: Authentication & Session | C14: Login | D14: 1.1.13 | E14: Admin login is never late | F14: Admin logs in after start time | G14: LoginLog with isLate=false (admins exempt) | H14: Medium | I14: ☐ | J14: ☐ | K14: ☐ | L14: ☐ | M14: ☐ | N14: =IF(COUNTIF(I14:L14,"☑")=4,"Complete",IF(COUNTIF(I14:L14,"☑")>0,"In Progress","Pending")) -> Pending
A15: 14 | B15: Authentication & Session | C15: Logout | D15: 1.2.1 | E15: Normal logout | F15: Click logout | G15: Session destroyed, LoginLog updated with logoutAt | H15: High | I15: ☐ | J15: ☐ | K15: ☑ | L15: ☐ | M15: ☐ | N15: =IF(COUNTIF(I15:L15,"☑")=4,"Complete",IF(COUNTIF(I15:L15,"☑")>0,"In Progress","Pending")) -> In Progress
A16: 15 | B16: Authentication & Session | C16: Logout | D16: 1.2.2 | E16: Record-logout API | F16: POST /api/auth/record-logout | G16: logoutAt timestamp updated on latest LoginLog | H16: High | I16: ☐ | J16: ☐ | K16: ☐ | L16: ☐ | M16: ☐ | N16: =IF(COUNTIF(I16:L16,"☑")=4,"Complete",IF(COUNTIF(I16:L16,"☑")>0,"In Progress","Pending")) -> Pending
A17: 16 | B17: Authentication & Session | C17: Password Reset | D17: 1.3.1 | E17: Request password reset | F17: Go to /forgot, enter valid email/username | G17: Reset email sent, PasswordResetToken created | H17: High | I17: ☐ | J17: ☐ | K17: ☐ | L17: ☐ | M17: ☐ | N17: =IF(COUNTIF(I17:L17,"☑")=4,"Complete",IF(COUNTIF(I17:L17,"☑")>0,"In Progress","Pending")) -> Pending | O17: "something went wrong" errror msg displayed
A18: 17 | B18: Authentication & Session | C18: Password Reset | D18: 1.3.2 | E18: Invalid identifier | F18: Enter non-existent email | G18: Vague success message (no user enumeration) | H18: High | I18: ☐ | J18: ☐ | K18: ☐ | L18: ☐ | M18: ☐ | N18: =IF(COUNTIF(I18:L18,"☑")=4,"Complete",IF(COUNTIF(I18:L18,"☑")>0,"In Progress","Pending")) -> Pending | O18: "something went wrong" errror msg displayed
A19: 18 | B19: Authentication & Session | C19: Password Reset | D19: 1.3.3 | E19: Complete reset with valid token | F19: Follow reset link, enter new password | G19: Password updated, token consumed | H19: High | I19: ☐ | J19: ☐ | K19: ☐ | L19: ☐ | M19: ☐ | N19: =IF(COUNTIF(I19:L19,"☑")=4,"Complete",IF(COUNTIF(I19:L19,"☑")>0,"In Progress","Pending")) -> Pending | O19: "something went wrong" errror msg displayed
A20: 19 | B20: Authentication & Session | C20: Password Reset | D20: 1.3.4 | E20: Expired/invalid token | F20: Use expired or tampered token | G20: Error message | H20: High | I20: ☐ | J20: ☐ | K20: ☐ | L20: ☐ | M20: ☐ | N20: =IF(COUNTIF(I20:L20,"☑")=4,"Complete",IF(COUNTIF(I20:L20,"☑")>0,"In Progress","Pending")) -> Pending
A21: 20 | B21: Authentication & Session | C21: Password Reset | D21: 1.3.5 | E21: Password mismatch | F21: New password ≠ confirm password | G21: Validation error | H21: Medium | I21: ☐ | J21: ☐ | K21: ☐ | L21: ☐ | M21: ☐ | N21: =IF(COUNTIF(I21:L21,"☑")=4,"Complete",IF(COUNTIF(I21:L21,"☑")>0,"In Progress","Pending")) -> Pending
A22: 21 | B22: Authentication & Session | C22: Session Management | D22: 1.4.1 | E22: Session idle timeout | F22: Leave session idle beyond configured timeout | G22: Redirect to login | H22: High | I22: ☐ | J22: ☐ | K22: ☐ | L22: ☐ | M22: ☐ | N22: =IF(COUNTIF(I22:L22,"☑")=4,"Complete",IF(COUNTIF(I22:L22,"☑")>0,"In Progress","Pending")) -> Pending
A23: 22 | B23: Authentication & Session | C23: Session Management | D23: 1.4.2 | E23: Forced password change blocks navigation | F23: User with mustChangePassword=true tries to navigate away from /account/security | G23: Redirected back to /account/security | H23: High | I23: ☐ | J23: ☐ | K23: ☐ | L23: ☐ | M23: ☐ | N23: =IF(COUNTIF(I23:L23,"☑")=4,"Complete",IF(COUNTIF(I23:L23,"☑")>0,"In Progress","Pending")) -> Pending
A24: 23 | B24: User Management | C24: Create User (saveUser) | D24: 2.1.1 | E24: Create user with all fields | F24: Fill fullName, email, username, role, phone, employeeCode, parentId, joiningDate, password | G24: User created, audit logged, revalidate /users | H24: Critical | I24: ☐ | J24: ☐ | K24: ☐ | L24: ☐ | M24: ☐ | N24: =IF(COUNTIF(I24:L24,"☑")=4,"Complete",IF(COUNTIF(I24:L24,"☑")>0,"In Progress","Pending")) -> Pending | O24: "something went wrong" errror msg displayed
A25: 24 | B25: User Management | C25: Create User (saveUser) | D25: 2.1.2 | E25: Missing full name | F25: Omit fullName | G25: Error: "Full name is required." | H25: High | I25: ☑ | J25: ☐ | K25: ☐ | L25: ☐ | M25: ☐ | N25: =IF(COUNTIF(I25:L25,"☑")=4,"Complete",IF(COUNTIF(I25:L25,"☑")>0,"In Progress","Pending")) -> In Progress | O25: not proper msg will be generate "please fill in this filed" this error msg will be generate
A26: 25 | B26: User Management | C26: Create User (saveUser) | D26: 2.1.3 | E26: Missing email | F26: Omit email | G26: Error: "Email is required." | H26: High | I26: ☑ | J26: ☐ | K26: ☐ | L26: ☐ | M26: ☐ | N26: =IF(COUNTIF(I26:L26,"☑")=4,"Complete",IF(COUNTIF(I26:L26,"☑")>0,"In Progress","Pending")) -> In Progress | O26: not proper msg will be generate "please fill in this filed" this error msg will be generate
A27: 26 | B27: User Management | C27: Create User (saveUser) | D27: 2.1.4 | E27: Missing username | F27: Omit username | G27: Error: "Username is required." | H27: High | I27: ☑ | J27: ☐ | K27: ☐ | L27: ☐ | M27: ☐ | N27: =IF(COUNTIF(I27:L27,"☑")=4,"Complete",IF(COUNTIF(I27:L27,"☑")>0,"In Progress","Pending")) -> In Progress | O27: not proper msg will be generate "please fill in this filed" this error msg will be generate
A28: 27 | B28: User Management | C28: Create User (saveUser) | D28: 2.1.5 | E28: Invalid role | F28: Set role to "SUPERADMIN" | G28: Error: "Select a valid role." | H28: High | I28: ☑ | J28: ☐ | K28: ☐ | L28: ☐ | M28: ☐ | N28: =IF(COUNTIF(I28:L28,"☑")=4,"Complete",IF(COUNTIF(I28:L28,"☑")>0,"In Progress","Pending")) -> In Progress | O28: not proper msg will be generate "please select an item in the list" this error msg will be generate
A29: 28 | B29: User Management | C29: Create User (saveUser) | D29: 2.1.6 | E29: Missing password on create | F29: Omit password for new user | G29: Error: "Password is required." | H29: High | I29: ☑ | J29: ☐ | K29: ☐ | L29: ☐ | M29: ☐ | N29: =IF(COUNTIF(I29:L29,"☑")=4,"Complete",IF(COUNTIF(I29:L29,"☑")>0,"In Progress","Pending")) -> In Progress | O29: not proper msg will be generate "please fill in this filed" this error msg will be generate
A30: 29 | B30: User Management | C30: Create User (saveUser) | D30: 2.1.7 | E30: Duplicate email | F30: Use email already in database | G30: Prisma unique constraint error | H30: High | I30: ☐ | J30: ☐ | K30: ☐ | L30: ☐ | M30: ☐ | N30: =IF(COUNTIF(I30:L30,"☑")=4,"Complete",IF(COUNTIF(I30:L30,"☑")>0,"In Progress","Pending")) -> Pending | O30: "something went wrong" errror msg displayed
A31: 30 | B31: User Management | C31: Create User (saveUser) | D31: 2.1.8 | E31: Duplicate username | F31: Use username already in database | G31: Prisma unique constraint error | H31: High | I31: ☐ | J31: ☐ | K31: ☐ | L31: ☐ | M31: ☐ | N31: =IF(COUNTIF(I31:L31,"☑")=4,"Complete",IF(COUNTIF(I31:L31,"☑")>0,"In Progress","Pending")) -> Pending | O31: "something went wrong" errror msg displayed
A32: 31 | B32: User Management | C32: Create User (saveUser) | D32: 2.1.9 | E32: Create with each valid role | F32: Test ADMIN, MANAGER, TEAM_LEADER, RECRUITER, ACCOUNTANT | G32: Each role accepted | H32: High | I32: ☑ | J32: ☐ | K32: ☐ | L32: ☐ | M32: ☐ | N32: =IF(COUNTIF(I32:L32,"☑")=4,"Complete",IF(COUNTIF(I32:L32,"☑")>0,"In Progress","Pending")) -> In Progress
A33: 32 | B33: User Management | C33: Create User (saveUser) | D33: 2.1.10 | E33: Optional fields omitted | F33: Create with only required fields | G33: User created with null optional fields | H33: Medium | I33: ☐ | J33: ☐ | K33: ☐ | L33: ☐ | M33: ☐ | N33: =IF(COUNTIF(I33:L33,"☑")=4,"Complete",IF(COUNTIF(I33:L33,"☑")>0,"In Progress","Pending")) -> Pending | O33: "something went wrong" errror msg displayed
A34: 33 | B34: User Management | C34: Update User (saveUser with userId) | D34: 2.2.1 | E34: Update name and role | F34: Set userId + new fullName + new role | G34: User updated, audit logs before/after | H34: High | I34: ☐ | J34: ☐ | K34: ☐ | L34: ☐ | M34: ☐ | N34: =IF(COUNTIF(I34:L34,"☑")=4,"Complete",IF(COUNTIF(I34:L34,"☑")>0,"In Progress","Pending")) -> Pending | O34: "something went wrong" errror msg displayed
A35: 34 | B35: User Management | C35: Update User (saveUser with userId) | D35: 2.2.2 | E35: Update password | F35: Set new password on existing user | G35: hashedPassword updated, passwordChangedAt reset, failedLoginAttempts=0, lockedUntil=null | H35: High | I35: ☐ | J35: ☐ | K35: ☐ | L35: ☐ | M35: ☐ | N35: =IF(COUNTIF(I35:L35,"☑")=4,"Complete",IF(COUNTIF(I35:L35,"☑")>0,"In Progress","Pending")) -> Pending | O35: "something went wrong" errror msg displayed
A36: 35 | B36: User Management | C36: Update User (saveUser with userId) | D36: 2.2.3 | E36: Update without password | F36: Omit password field on existing user | G36: Password unchanged | H36: Medium | I36: ☐ | J36: ☐ | K36: ☐ | L36: ☐ | M36: ☐ | N36: =IF(COUNTIF(I36:L36,"☑")=4,"Complete",IF(COUNTIF(I36:L36,"☑")>0,"In Progress","Pending")) -> Pending | O36: "something went wrong" errror msg displayed
A37: 36 | B37: User Management | C37: Update User (saveUser with userId) | D37: 2.2.4 | E37: Non-existent userId | F37: Set userId to invalid ID | G37: Prisma error (record not found) | H37: Medium | I37: ☐ | J37: ☐ | K37: ☐ | L37: ☐ | M37: ☐ | N37: =IF(COUNTIF(I37:L37,"☑")=4,"Complete",IF(COUNTIF(I37:L37,"☑")>0,"In Progress","Pending")) -> Pending | O37: "something went wrong" errror msg displayed
A38: 37 | B38: User Management | C38: Toggle User (toggleUser) | D38: 2.3.1 | E38: Deactivate user | F38: toggleUser(userId, false) | G38: isActive=false, audit logged | H38: High | I38: ☐ | J38: ☐ | K38: ☐ | L38: ☐ | M38: ☐ | N38: =IF(COUNTIF(I38:L38,"☑")=4,"Complete",IF(COUNTIF(I38:L38,"☑")>0,"In Progress","Pending")) -> Pending | O38: users:1 Failed to load resource: the server responded with a status of 500 ()
A39: 38 | B39: User Management | C39: Toggle User (toggleUser) | D39: 2.3.2 | E39: Reactivate user | F39: toggleUser(userId, true) | G39: isActive=true, audit logged | H39: High | I39: ☐ | J39: ☐ | K39: ☐ | L39: ☐ | M39: ☐ | N39: =IF(COUNTIF(I39:L39,"☑")=4,"Complete",IF(COUNTIF(I39:L39,"☑")>0,"In Progress","Pending")) -> Pending
A40: 39 | B40: User Management | C40: Toggle User (toggleUser) | D40: 2.3.3 | E40: Toggle non-existent user | F40: Pass invalid userId | G40: Error: "User not found." | H40: Medium | I40: ☐ | J40: ☐ | K40: ☐ | L40: ☐ | M40: ☐ | N40: =IF(COUNTIF(I40:L40,"☑")=4,"Complete",IF(COUNTIF(I40:L40,"☑")>0,"In Progress","Pending")) -> Pending
A41: 40 | B41: User Management | C41: Employee Schedule (saveEmployeeSchedule) | D41: 2.4.1 | E41: Create schedule | F41: Set userId, startTime, endTime, day_1..day_5, graceMinutes | G41: EmployeeSchedule created via upsert, audit logged | H41: High | I41: ☐ | J41: ☐ | K41: ☐ | L41: ☐ | M41: ☐ | N41: =IF(COUNTIF(I41:L41,"☑")=4,"Complete",IF(COUNTIF(I41:L41,"☑")>0,"In Progress","Pending")) -> Pending | O41: "something went wrong" errror msg displayed
A42: 41 | B42: User Management | C42: Employee Schedule (saveEmployeeSchedule) | D42: 2.4.2 | E42: Update existing schedule | F42: Change times on user with existing schedule | G42: Schedule updated (upsert) | H42: High | I42: ☐ | J42: ☐ | K42: ☐ | L42: ☐ | M42: ☐ | N42: =IF(COUNTIF(I42:L42,"☑")=4,"Complete",IF(COUNTIF(I42:L42,"☑")>0,"In Progress","Pending")) -> Pending | O42: "something went wrong" errror msg displayed
A43: 42 | B43: User Management | C43: Employee Schedule (saveEmployeeSchedule) | D43: 2.4.3 | E43: Missing user | F43: Omit userId | G43: Error: "User is required." | H43: Medium | I43: ☐ | J43: ☐ | K43: ☐ | L43: ☐ | M43: ☐ | N43: =IF(COUNTIF(I43:L43,"☑")=4,"Complete",IF(COUNTIF(I43:L43,"☑")>0,"In Progress","Pending")) -> Pending
A44: 43 | B44: User Management | C44: Employee Schedule (saveEmployeeSchedule) | D44: 2.4.4 | E44: Missing start time | F44: Omit workStartTime | G44: Error: "Start and end time are required." | H44: Medium | I44: ☐ | J44: ☐ | K44: ☐ | L44: ☐ | M44: ☐ | N44: =IF(COUNTIF(I44:L44,"☑")=4,"Complete",IF(COUNTIF(I44:L44,"☑")>0,"In Progress","Pending")) -> Pending
A45: 44 | B45: User Management | C45: Employee Schedule (saveEmployeeSchedule) | D45: 2.4.5 | E45: No working days selected | F45: Omit all day_1 through day_7 | G45: Error: "Select at least one working day." | H45: Medium | I45: ☐ | J45: ☐ | K45: ☐ | L45: ☐ | M45: ☐ | N45: =IF(COUNTIF(I45:L45,"☑")=4,"Complete",IF(COUNTIF(I45:L45,"☑")>0,"In Progress","Pending")) -> Pending
A46: 45 | B46: User Management | C46: Employee Schedule (saveEmployeeSchedule) | D46: 2.4.6 | E46: Remove schedule | F46: removeEmployeeSchedule with valid userId | G46: Schedule deleted, fallback to global | H46: Medium | I46: ☐ | J46: ☐ | K46: ☐ | L46: ☐ | M46: ☐ | N46: =IF(COUNTIF(I46:L46,"☑")=4,"Complete",IF(COUNTIF(I46:L46,"☑")>0,"In Progress","Pending")) -> Pending | O46: the schedule is not getting added, I can't check why it's not getting removed yet
A47: 46 | B47: User Management | C47: Employee Schedule (saveEmployeeSchedule) | D47: 2.4.7 | E47: Remove non-existent schedule | F47: Remove for user without custom schedule | G47: Success: "Already using global defaults." | H47: Low | I47: ☐ | J47: ☐ | K47: ☐ | L47: ☐ | M47: ☐ | N47: =IF(COUNTIF(I47:L47,"☑")=4,"Complete",IF(COUNTIF(I47:L47,"☑")>0,"In Progress","Pending")) -> Pending | O47: the schedule is not getting added, I can't check why it's not getting removed yet
A48: 47 | B48: RBAC & Permissions | D48: 3.1 | E48: ADMIN has all permissions | F48: Check can("ADMIN", perm) for every permission | G48: All return true | H48: Critical | I48: ☑ | J48: ☐ | K48: ☑ | L48: ☐ | M48: ☐ | N48: =IF(COUNTIF(I48:L48,"☑")=4,"Complete",IF(COUNTIF(I48:L48,"☑")>0,"In Progress","Pending")) -> In Progress
A49: 48 | B49: RBAC & Permissions | D49: 3.2 | E49: RECRUITER cannot manage users | F49: can("RECRUITER", "users:manage") | G49: Returns false/undefined | H49: Critical | I49: ☑ | J49: ☐ | K49: ☐ | L49: ☐ | M49: ☐ | N49: =IF(COUNTIF(I49:L49,"☑")=4,"Complete",IF(COUNTIF(I49:L49,"☑")>0,"In Progress","Pending")) -> In Progress
A50: 49 | B50: RBAC & Permissions | D50: 3.3 | E50: RECRUITER can create candidates | F50: can("RECRUITER", "candidates:create") | G50: Returns true | H50: High | I50: ☑ | J50: ☐ | K50: ☐ | L50: ☐ | M50: ☐ | N50: =IF(COUNTIF(I50:L50,"☑")=4,"Complete",IF(COUNTIF(I50:L50,"☑")>0,"In Progress","Pending")) -> In Progress
A51: 50 | B51: RBAC & Permissions | D51: 3.4 | E51: ACCOUNTANT has billing:full | F51: can("ACCOUNTANT", "billing:full") | G51: Returns true | H51: High | I51: ☑ | J51: ☐ | K51: ☐ | L51: ☐ | M51: ☐ | N51: =IF(COUNTIF(I51:L51,"☑")=4,"Complete",IF(COUNTIF(I51:L51,"☑")>0,"In Progress","Pending")) -> In Progress
A52: 51 | B52: RBAC & Permissions | D52: 3.5 | E52: ACCOUNTANT cannot manage attendance | F52: can("ACCOUNTANT", "attendance:manage") | G52: Returns false | H52: High | I52: ☑ | J52: ☐ | K52: ☐ | L52: ☐ | M52: ☐ | N52: =IF(COUNTIF(I52:L52,"☑")=4,"Complete",IF(COUNTIF(I52:L52,"☑")>0,"In Progress","Pending")) -> In Progress
A53: 52 | B53: RBAC & Permissions | D53: 3.6 | E53: MANAGER cannot manage billing | F53: can("MANAGER", "billing:full") | G53: Returns false | H53: High | I53: ☑ | J53: ☐ | K53: ☐ | L53: ☐ | M53: ☐ | N53: =IF(COUNTIF(I53:L53,"☑")=4,"Complete",IF(COUNTIF(I53:L53,"☑")>0,"In Progress","Pending")) -> In Progress
A54: 53 | B54: RBAC & Permissions | D54: 3.7 | E54: TEAM_LEADER can assign jobs | F54: can("TEAM_LEADER", "jobs:assign") | G54: Returns true | H54: High | I54: ☐ | J54: ☐ | K54: ☐ | L54: ☐ | M54: ☐ | N54: =IF(COUNTIF(I54:L54,"☑")=4,"Complete",IF(COUNTIF(I54:L54,"☑")>0,"In Progress","Pending")) -> Pending
A55: 54 | B55: RBAC & Permissions | D55: 3.8 | E55: TEAM_LEADER cannot create jobs | F55: can("TEAM_LEADER", "jobs:full") | G55: Returns false | H55: High | I55: ☐ | J55: ☐ | K55: ☐ | L55: ☐ | M55: ☐ | N55: =IF(COUNTIF(I55:L55,"☑")=4,"Complete",IF(COUNTIF(I55:L55,"☑")>0,"In Progress","Pending")) -> Pending | O55: "something went wrong" errror msg displayed
A56: 55 | B56: RBAC & Permissions | D56: 3.9 | E56: Invalid role string | F56: isPortalRole("SUPERADMIN") | G56: Returns false | H56: Medium | I56: ☐ | J56: ☐ | K56: ☐ | L56: ☐ | M56: ☐ | N56: =IF(COUNTIF(I56:L56,"☑")=4,"Complete",IF(COUNTIF(I56:L56,"☑")>0,"In Progress","Pending")) -> Pending
A57: 56 | B57: RBAC & Permissions | D57: 3.10 | E57: Undefined role | F57: isPortalRole(undefined) | G57: Returns false | H57: Medium | I57: ☐ | J57: ☐ | K57: ☐ | L57: ☐ | M57: ☐ | N57: =IF(COUNTIF(I57:L57,"☑")=4,"Complete",IF(COUNTIF(I57:L57,"☑")>0,"In Progress","Pending")) -> Pending
A58: 57 | B58: RBAC & Permissions | C58: Permission Enforcement on Server Actions | D58: 3.11.1 | E58: RECRUITER calls saveUser | F58: Login as RECRUITER, call saveUser action | G58: Error: "Admin permissions are required." | H58: Critical | I58: ☐ | J58: ☐ | K58: ☐ | L58: ☐ | M58: ☐ | N58: =IF(COUNTIF(I58:L58,"☑")=4,"Complete",IF(COUNTIF(I58:L58,"☑")>0,"In Progress","Pending")) -> Pending | O58: no user option to create an user
A59: 58 | B59: RBAC & Permissions | C59: Permission Enforcement on Server Actions | D59: 3.11.2 | E59: RECRUITER calls grantLeaveAction | F59: Login as RECRUITER, call grantLeaveAction | G59: Error: "Permission denied" | H59: Critical | I59: ☐ | J59: ☐ | K59: ☐ | L59: ☐ | M59: ☐ | N59: =IF(COUNTIF(I59:L59,"☑")=4,"Complete",IF(COUNTIF(I59:L59,"☑")>0,"In Progress","Pending")) -> Pending | O59: recruiter have no option to grant leave
A60: 59 | B60: RBAC & Permissions | C60: Permission Enforcement on Server Actions | D60: 3.11.3 | E60: RECRUITER calls createClient | F60: Login as RECRUITER, call createClient | G60: Error: "You do not have permission to modify client records." | H60: Critical | I60: ☐ | J60: ☐ | K60: ☐ | L60: ☐ | M60: ☐ | N60: =IF(COUNTIF(I60:L60,"☑")=4,"Complete",IF(COUNTIF(I60:L60,"☑")>0,"In Progress","Pending")) -> Pending
A61: 60 | B61: RBAC & Permissions | C61: Permission Enforcement on Server Actions | D61: 3.11.4 | E61: RECRUITER calls createCandidate | F61: Login as RECRUITER, call createCandidate | G61: Succeeds (has candidates:create) | H61: High | I61: ☐ | J61: ☐ | K61: ☐ | L61: ☐ | M61: ☐ | N61: =IF(COUNTIF(I61:L61,"☑")=4,"Complete",IF(COUNTIF(I61:L61,"☑")>0,"In Progress","Pending")) -> Pending | O61: "something went wrong" errror msg displayed
A62: 61 | B62: RBAC & Permissions | C62: Permission Enforcement on Server Actions | D62: 3.11.5 | E62: ACCOUNTANT calls createInvoice | F62: Login as ACCOUNTANT, call createInvoice | G62: Succeeds (has billing:full) | H62: High | I62: ☑ | J62: ☐ | K62: ☐ | L62: ☐ | M62: ☐ | N62: =IF(COUNTIF(I62:L62,"☑")=4,"Complete",IF(COUNTIF(I62:L62,"☑")>0,"In Progress","Pending")) -> In Progress
A63: 62 | B63: RBAC & Permissions | C63: Permission Enforcement on Server Actions | D63: 3.11.6 | E63: MANAGER calls updateJobStatus | F63: Login as MANAGER, call updateJobStatus | G63: Succeeds (has jobs:full) | H63: High | I63: ☑ | J63: ☐ | K63: ☐ | L63: ☐ | M63: ☐ | N63: =IF(COUNTIF(I63:L63,"☑")=4,"Complete",IF(COUNTIF(I63:L63,"☑")>0,"In Progress","Pending")) -> In Progress
A64: 63 | B64: RBAC & Permissions | C64: Permission Enforcement on Server Actions | D64: 3.11.7 | E64: TEAM_LEADER calls bulkUpdateCandidateStatus | F64: Login as TL, call bulkUpdateCandidateStatus | G64: Succeeds (has candidates:full) | H64: High | I64: ☐ | J64: ☐ | K64: ☐ | L64: ☐ | M64: ☐ | N64: =IF(COUNTIF(I64:L64,"☑")=4,"Complete",IF(COUNTIF(I64:L64,"☑")>0,"In Progress","Pending")) -> Pending | O64: i uploaded valid file but still comes up issue "name is required"
A65: 64 | B65: RBAC & Permissions | C65: Permission Enforcement on Server Actions | D65: 3.11.8 | E65: Unauthenticated request | F65: No session, call any server action | G65: Error: permission denied or session error | H65: Critical | I65: ☐ | J65: ☐ | K65: ☐ | L65: ☐ | M65: ☐ | N65: =IF(COUNTIF(I65:L65,"☑")=4,"Complete",IF(COUNTIF(I65:L65,"☑")>0,"In Progress","Pending")) -> Pending
A66: 65 | B66: Client Management | C66: Create Client (createClient) | D66: 4.1.1 | E66: Valid client with all fields | F66: Fill all required fields + MSA file upload | G66: Client created, clientCode generated (e.g. TCS00001), MSA record created, audit logged | H66: Critical | I66: ☑ | J66: ☐ | K66: ☐ | L66: ☐ | M66: ☐ | N66: =IF(COUNTIF(I66:L66,"☑")=4,"Complete",IF(COUNTIF(I66:L66,"☑")>0,"In Progress","Pending")) -> In Progress
A67: 66 | B67: Client Management | C67: Create Client (createClient) | D67: 4.1.2 | E67: Missing client name | F67: Omit name | G67: Error: "Client name is required" | H67: High | I67: ☑ | J67: ☐ | K67: ☐ | L67: ☐ | M67: ☐ | N67: =IF(COUNTIF(I67:L67,"☑")=4,"Complete",IF(COUNTIF(I67:L67,"☑")>0,"In Progress","Pending")) -> In Progress
A68: 67 | B68: Client Management | C68: Create Client (createClient) | D68: 4.1.3 | E68: Missing primary contact | F68: Omit primaryContactName, Phone, or Email | G68: Error for respective field | H68: High | I68: ☑ | J68: ☐ | K68: ☐ | L68: ☐ | M68: ☐ | N68: =IF(COUNTIF(I68:L68,"☑")=4,"Complete",IF(COUNTIF(I68:L68,"☑")>0,"In Progress","Pending")) -> In Progress | O68: accepting negative number
A69: 68 | B69: Client Management | C69: Create Client (createClient) | D69: 4.1.4 | E69: Missing GST number | F69: Omit gstNumber | G69: Error: "GST number is required" | H69: High | I69: ☑ | J69: ☐ | K69: ☐ | L69: ☐ | M69: ☐ | N69: =IF(COUNTIF(I69:L69,"☑")=4,"Complete",IF(COUNTIF(I69:L69,"☑")>0,"In Progress","Pending")) -> In Progress | O69: accepting negative number
A70: 69 | B70: Client Management | C70: Create Client (createClient) | D70: 4.1.5 | E70: Missing PAN number | F70: Omit panNumber | G70: Error: "PAN number is required" | H70: High | I70: ☑ | J70: ☐ | K70: ☐ | L70: ☐ | M70: ☐ | N70: =IF(COUNTIF(I70:L70,"☑")=4,"Complete",IF(COUNTIF(I70:L70,"☑")>0,"In Progress","Pending")) -> In Progress
A71: 70 | B71: Client Management | C71: Create Client (createClient) | D71: 4.1.6 | E71: Missing address | F71: Omit address | G71: Error: "Address is required" | H71: High | I71: ☑ | J71: ☐ | K71: ☐ | L71: ☐ | M71: ☐ | N71: =IF(COUNTIF(I71:L71,"☑")=4,"Complete",IF(COUNTIF(I71:L71,"☑")>0,"In Progress","Pending")) -> In Progress
A72: 71 | B72: Client Management | C72: Create Client (createClient) | D72: 4.1.7 | E72: No industries selected | F72: Submit empty industries array | G72: Error: "Select at least one industry" | H72: High | I72: ☑ | J72: ☐ | K72: ☐ | L72: ☐ | M72: ☐ | N72: =IF(COUNTIF(I72:L72,"☑")=4,"Complete",IF(COUNTIF(I72:L72,"☑")>0,"In Progress","Pending")) -> In Progress
A73: 72 | B73: Client Management | C73: Create Client (createClient) | D73: 4.1.8 | E73: Missing MSA dates | F73: Omit msaStart or msaEnd | G73: Error: "MSA dates are required" | H73: High | I73: ☑ | J73: ☐ | K73: ☐ | L73: ☐ | M73: ☐ | N73: =IF(COUNTIF(I73:L73,"☑")=4,"Complete",IF(COUNTIF(I73:L73,"☑")>0,"In Progress","Pending")) -> In Progress
A74: 73 | B74: Client Management | C74: Create Client (createClient) | D74: 4.1.9 | E74: Client without MSA file | F74: Submit without file (only dates) | G74: Client created without ClientMSA record, client still has msaStartDate/msaEndDate | H74: Medium | I74: ☑ | J74: ☐ | K74: ☐ | L74: ☐ | M74: ☐ | N74: =IF(COUNTIF(I74:L74,"☑")=4,"Complete",IF(COUNTIF(I74:L74,"☑")>0,"In Progress","Pending")) -> In Progress
A75: 74 | B75: Client Management | C75: Create Client (createClient) | D75: 4.1.10 | E75: Optional secondary contact | F75: Fill only primary contact fields | G75: Client created with null secondary fields | H75: Low | I75: ☑ | J75: ☐ | K75: ☐ | L75: ☐ | M75: ☐ | N75: =IF(COUNTIF(I75:L75,"☑")=4,"Complete",IF(COUNTIF(I75:L75,"☑")>0,"In Progress","Pending")) -> In Progress
A76: 75 | B76: Client Management | C76: Create Client (createClient) | D76: 4.1.11 | E76: Client code uniqueness | F76: Create two clients with same name prefix | G76: Both get unique codes (TCS00001, TCS00002) | H76: High | I76: ☑ | J76: ☐ | K76: ☐ | L76: ☐ | M76: ☐ | N76: =IF(COUNTIF(I76:L76,"☑")=4,"Complete",IF(COUNTIF(I76:L76,"☑")>0,"In Progress","Pending")) -> In Progress
A77: 76 | B77: Client Management | C77: Toggle Client Status (toggleClientStatus) | D77: 4.2.1 | E77: Deactivate client | F77: toggleClientStatus(id, "INACTIVE") | G77: Status changed, audit logged with before/after | H77: High | I77: ☑ | J77: ☐ | K77: ☐ | L77: ☐ | M77: ☐ | N77: =IF(COUNTIF(I77:L77,"☑")=4,"Complete",IF(COUNTIF(I77:L77,"☑")>0,"In Progress","Pending")) -> In Progress
A78: 77 | B78: Client Management | C78: Toggle Client Status (toggleClientStatus) | D78: 4.2.2 | E78: Reactivate client | F78: toggleClientStatus(id, "ACTIVE") | G78: Status changed back | H78: High | I78: ☑ | J78: ☐ | K78: ☐ | L78: ☐ | M78: ☐ | N78: =IF(COUNTIF(I78:L78,"☑")=4,"Complete",IF(COUNTIF(I78:L78,"☑")>0,"In Progress","Pending")) -> In Progress
A79: 78 | B79: Client Management | C79: Toggle Client Status (toggleClientStatus) | D79: 4.2.3 | E79: Invalid client ID | F79: Pass non-existent ID | G79: Prisma error (record not found) | H79: Medium | I79: ☐ | J79: ☐ | K79: ☐ | L79: ☐ | M79: ☐ | N79: =IF(COUNTIF(I79:L79,"☑")=4,"Complete",IF(COUNTIF(I79:L79,"☑")>0,"In Progress","Pending")) -> Pending
A80: 79 | B80: Client Management | C80: MSA Reminder Digest (sendMsaReminderDigest) | D80: 4.3.1 | E80: Clients within 60-day window | F80: Create client with MSA ending in < 60 days, run digest | G80: Email sent with summary | H80: High | I80: ☐ | J80: ☐ | K80: ☐ | L80: ☐ | M80: ☐ | N80: =IF(COUNTIF(I80:L80,"☑")=4,"Complete",IF(COUNTIF(I80:L80,"☑")>0,"In Progress","Pending")) -> Pending | O80: The email is clickable, but I'm unable to verify if the email was sent
A81: 80 | B81: Client Management | C81: MSA Reminder Digest (sendMsaReminderDigest) | D81: 4.3.2 | E81: No clients in window | F81: All MSAs > 60 days out | G81: "No clients are within the 60-day MSA window." | H81: Medium | I81: ☐ | J81: ☐ | K81: ☐ | L81: ☐ | M81: ☐ | N81: =IF(COUNTIF(I81:L81,"☑")=4,"Complete",IF(COUNTIF(I81:L81,"☑")>0,"In Progress","Pending")) -> Pending
A82: 81 | B82: Job Requirements | C82: Create Job (createJobRequirement) | D82: 5.1.1 | E82: Admin creates open job | F82: Login as ADMIN, fill all fields, status=OPEN | G82: Job created with status=OPEN | H82: Critical | I82: ☐ | J82: ☐ | K82: ☐ | L82: ☐ | M82: ☐ | N82: =IF(COUNTIF(I82:L82,"☑")=4,"Complete",IF(COUNTIF(I82:L82,"☑")>0,"In Progress","Pending")) -> Pending | O82: "something went wrong" errror msg displayed
A83: 82 | B83: Job Requirements | C83: Create Job (createJobRequirement) | D83: 5.1.2 | E83: Non-admin creates job | F83: Login as MANAGER, create job with status=OPEN | G83: Job created with status=PENDING_APPROVAL (forced) | H83: Critical | I83: ☐ | J83: ☐ | K83: ☐ | L83: ☐ | M83: ☐ | N83: =IF(COUNTIF(I83:L83,"☑")=4,"Complete",IF(COUNTIF(I83:L83,"☑")>0,"In Progress","Pending")) -> Pending | O83: "something went wrong" errror msg displayed
A84: 83 | B84: Job Requirements | C84: Create Job (createJobRequirement) | D84: 5.1.3 | E84: Missing client | F84: Omit client | G84: Error: "Client is required." | H84: High | I84: ☑ | J84: ☐ | K84: ☐ | L84: ☐ | M84: ☐ | N84: =IF(COUNTIF(I84:L84,"☑")=4,"Complete",IF(COUNTIF(I84:L84,"☑")>0,"In Progress","Pending")) -> In Progress | O84: not proper msg will be generate "please select an item in the list" this error msg will be generate
A85: 84 | B85: Job Requirements | C85: Create Job (createJobRequirement) | D85: 5.1.4 | E85: Missing position title | F85: Omit positionTitle | G85: Error: "Position title is required." | H85: High | I85: ☑ | J85: ☐ | K85: ☐ | L85: ☐ | M85: ☐ | N85: =IF(COUNTIF(I85:L85,"☑")=4,"Complete",IF(COUNTIF(I85:L85,"☑")>0,"In Progress","Pending")) -> In Progress | O85: not proper msg will be generate "please fill in this filed" this error msg will be generate
A86: 85 | B86: Job Requirements | C86: Create Job (createJobRequirement) | D86: 5.1.5 | E86: Zero openings | F86: Set openings=0 | G86: Error: "Openings must be a positive integer." | H86: High | I86: ☑ | J86: ☐ | K86: ☐ | L86: ☐ | M86: ☐ | N86: =IF(COUNTIF(I86:L86,"☑")=4,"Complete",IF(COUNTIF(I86:L86,"☑")>0,"In Progress","Pending")) -> In Progress
A87: 86 | B87: Job Requirements | C87: Create Job (createJobRequirement) | D87: 5.1.6 | E87: Negative openings | F87: Set openings=-1 | G87: Error: "Openings must be a positive integer." | H87: High | I87: ☑ | J87: ☐ | K87: ☐ | L87: ☐ | M87: ☐ | N87: =IF(COUNTIF(I87:L87,"☑")=4,"Complete",IF(COUNTIF(I87:L87,"☑")>0,"In Progress","Pending")) -> In Progress
A88: 87 | B88: Job Requirements | C88: Create Job (createJobRequirement) | D88: 5.1.7 | E88: Non-integer openings | F88: Set openings=1.5 | G88: Error: "Openings must be a positive integer." | H88: Medium | I88: ☑ | J88: ☐ | K88: ☐ | L88: ☐ | M88: ☐ | N88: =IF(COUNTIF(I88:L88,"☑")=4,"Complete",IF(COUNTIF(I88:L88,"☑")>0,"In Progress","Pending")) -> In Progress
A89: 88 | B89: Job Requirements | C89: Create Job (createJobRequirement) | D89: 5.1.8 | E89: Missing location | F89: Omit location | G89: Error: "Location is required." | H89: High | I89: ☑ | J89: ☐ | K89: ☐ | L89: ☐ | M89: ☐ | N89: =IF(COUNTIF(I89:L89,"☑")=4,"Complete",IF(COUNTIF(I89:L89,"☑")>0,"In Progress","Pending")) -> In Progress | O89: not proper msg will be generate "please fill in this filed" this error msg will be generate
A90: 89 | B90: Job Requirements | C90: Create Job (createJobRequirement) | D90: 5.1.9 | E90: Experience min > max | F90: Set min=10, max=5 | G90: Error: "Experience min cannot exceed max." | H90: High | I90: ☐ | J90: ☐ | K90: ☐ | L90: ☐ | M90: ☐ | N90: =IF(COUNTIF(I90:L90,"☑")=4,"Complete",IF(COUNTIF(I90:L90,"☑")>0,"In Progress","Pending")) -> Pending | O90: "something went wrong" errror msg displayed
A91: 90 | B91: Job Requirements | C91: Create Job (createJobRequirement) | D91: 5.1.10 | E91: Negative experience | F91: Set min=-1 | G91: Error: "Experience range must be numeric." | H91: Medium | I91: ☐ | J91: ☐ | K91: ☐ | L91: ☐ | M91: ☐ | N91: =IF(COUNTIF(I91:L91,"☑")=4,"Complete",IF(COUNTIF(I91:L91,"☑")>0,"In Progress","Pending")) -> Pending | O91: "something went wrong" errror msg displayed
A92: 91 | B92: Job Requirements | C92: Create Job (createJobRequirement) | D92: 5.1.11 | E92: Assign recruiters on create | F92: Pass recruiterIds array | G92: JobAssignment records created | H92: High | I92: ☐ | J92: ☐ | K92: ☐ | L92: ☐ | M92: ☐ | N92: =IF(COUNTIF(I92:L92,"☑")=4,"Complete",IF(COUNTIF(I92:L92,"☑")>0,"In Progress","Pending")) -> Pending | O92: "something went wrong" errror msg displayed
A93: 92 | B93: Job Requirements | C93: Create Job (createJobRequirement) | D93: 5.1.12 | E93: Job code generation | F93: Create job for client TCS | G93: jobCode like TCS0001, unique | H93: High | I93: ☐ | J93: ☐ | K93: ☐ | L93: ☐ | M93: ☐ | N93: =IF(COUNTIF(I93:L93,"☑")=4,"Complete",IF(COUNTIF(I93:L93,"☑")>0,"In Progress","Pending")) -> Pending | O93: I couldn't check it because the client is not being created.
A94: 93 | B94: Job Requirements | C94: Create Job (createJobRequirement) | D94: 5.1.13 | E94: Non-existent client | F94: Pass fake clientId | G94: Error: "Client not found." | H94: Medium | I94: ☑ | J94: ☐ | K94: ☐ | L94: ☐ | M94: ☐ | N94: =IF(COUNTIF(I94:L94,"☑")=4,"Complete",IF(COUNTIF(I94:L94,"☑")>0,"In Progress","Pending")) -> In Progress | O94: I couldn't check it because the job is not being created.
A95: 94 | B95: Job Requirements | C95: Job Status Transitions | D95: 5.2.1 | E95: Admin approves pending job | F95: approveJob(jobId) as ADMIN | G95: Status → OPEN | H95: Critical | I95: ☐ | J95: ☐ | K95: ☐ | L95: ☐ | M95: ☐ | N95: =IF(COUNTIF(I95:L95,"☑")=4,"Complete",IF(COUNTIF(I95:L95,"☑")>0,"In Progress","Pending")) -> Pending | O95: I couldn't check it because the job is not being created.
A96: 95 | B96: Job Requirements | C96: Job Status Transitions | D96: 5.2.2 | E96: Non-admin tries to approve | F96: approveJob(jobId) as MANAGER | G96: Error: "Only admins can approve jobs." | H96: Critical | I96: ☐ | J96: ☐ | K96: ☐ | L96: ☐ | M96: ☐ | N96: =IF(COUNTIF(I96:L96,"☑")=4,"Complete",IF(COUNTIF(I96:L96,"☑")>0,"In Progress","Pending")) -> Pending | O96: I couldn't check it because the job is not being created.
A97: 96 | B97: Job Requirements | C97: Job Status Transitions | D97: 5.2.3 | E97: Approve already-open job | F97: approveJob(jobId) where status=OPEN | G97: Error: "Only pending or on-hold jobs can be approved." | H97: High | I97: ☐ | J97: ☐ | K97: ☐ | L97: ☐ | M97: ☐ | N97: =IF(COUNTIF(I97:L97,"☑")=4,"Complete",IF(COUNTIF(I97:L97,"☑")>0,"In Progress","Pending")) -> Pending | O97: I couldn't check it because the job is not being created.
A98: 97 | B98: Job Requirements | C98: Job Status Transitions | D98: 5.2.4 | E98: Submit for approval | F98: submitJobForApproval(jobId) | G98: Status → PENDING_APPROVAL | H98: High | I98: ☐ | J98: ☐ | K98: ☐ | L98: ☐ | M98: ☐ | N98: =IF(COUNTIF(I98:L98,"☑")=4,"Complete",IF(COUNTIF(I98:L98,"☑")>0,"In Progress","Pending")) -> Pending | O98: I couldn't check it because the job is not being created.
A99: 98 | B99: Job Requirements | C99: Job Status Transitions | D99: 5.2.5 | E99: Submit already-open job | F99: submitJobForApproval(jobId) where status=OPEN | G99: Error: "Job is already open." | H99: Medium | I99: ☐ | J99: ☐ | K99: ☐ | L99: ☐ | M99: ☐ | N99: =IF(COUNTIF(I99:L99,"☑")=4,"Complete",IF(COUNTIF(I99:L99,"☑")>0,"In Progress","Pending")) -> Pending | O99: I couldn't check it because the job is not being created.
A100: 99 | B100: Job Requirements | C100: Job Status Transitions | D100: 5.2.6 | E100: Submit already-pending job | F100: submitJobForApproval(jobId) where status=PENDING_APPROVAL | G100: Error: "Job is already awaiting approval." | H100: Medium | I100: ☐ | J100: ☐ | K100: ☐ | L100: ☐ | M100: ☐ | N100: =IF(COUNTIF(I100:L100,"☑")=4,"Complete",IF(COUNTIF(I100:L100,"☑")>0,"In Progress","Pending")) -> Pending | O100: I couldn't check it because the job is not being created.
...

Sheet Summary
A1: Tester | B1: Completed | C1: Pending | D1: Total Checkpoints | E1: Completion %
A2: Manjali | B2: =COUNTIF('UAT Checklist'!I:I,"☑") -> 138 | C2: =COUNTIF('UAT Checklist'!I:I,"☐") -> 190 | D2: 328 | E2: =IF(D2=0,0,B2/D2) -> 0.42073171
A3: Aditi | B3: =COUNTIF('UAT Checklist'!J:J,"☑") -> 0 | C3: =COUNTIF('UAT Checklist'!J:J,"☐") -> 328 | D3: 328 | E3: =IF(D3=0,0,B3/D3) -> 0
A4: Siddhi | B4: =COUNTIF('UAT Checklist'!K:K,"☑") -> 8 | C4: =COUNTIF('UAT Checklist'!K:K,"☐") -> 320 | D4: 328 | E4: =IF(D4=0,0,B4/D4) -> 0.024390244
A5: Chinmay | B5: =COUNTIF('UAT Checklist'!L:L,"☑") -> 0 | C5: =COUNTIF('UAT Checklist'!L:L,"☐") -> 328 | D5: 328 | E5: =IF(D5=0,0,B5/D5) -> 0
A7: Overall complete rows | B7: =COUNTIF('UAT Checklist'!N:N,"Complete") -> 0
A8: Overall pending rows | B8: =COUNTIF('UAT Checklist'!N:N,"Pending") -> 189
A9: Overall in-progress rows | B9: =COUNTIF('UAT Checklist'!N:N,"In Progress") -> 139
A10: Source file | B10: ADMIN_TEST_CASES.md
A11: Note | B11: Use the dropdown in each tester column to switch unchecked to checked.
